ur_aj/__init__.py
ur_aj/core.py
ur_aj-0.1.5.dist-info/METADATA
ur_aj-0.1.5.dist-info/WHEEL
ur_aj-0.1.5.dist-info/top_level.txt
ur_aj-0.1.5.dist-info/RECORD
