Metadata-Version: 2.4
Name: ur-aj
Version: 0.1.5
Summary: Python library for controlling Universal Robots via sockets
Home-page: https://github.com/Akshaybhawarkiti/UR-aj
Author: Akshay Ajit Bhawar
Author-email: akshayfusion1@gmail.com
Classifier: Programming Language :: Python :: 3
Classifier: Operating System :: OS Independent
Requires-Python: >=3.7
Dynamic: author
Dynamic: author-email
Dynamic: classifier
Dynamic: description
Dynamic: description-content-type
Dynamic: home-page
Dynamic: requires-python
Dynamic: summary
